[
  {
    "slug": "fl-bdi",
    "state": "FL",
    "course_name": "Florida Basic Driver Improvement (English)",
    "course_type": "BDI",
    "language": "English",
    "provider_type": "Partner",
    "provider_name": "TicketSchool",
    "affiliate_partner": "TicketSchool",
    "partner_badge": "Provided by TicketSchool",
    "duration_hours": "4",
    "price_usd": "24.95",
    "eligibility": "Elective/court/DMV; eligible once every 12 months and max 5 times lifetime",
    "identity_verification": "10 ID questions; must answer ≥70% correctly during random checks",
    "reporting_method": "Electronic reporting to FL DHSMV after completion; student must notify court/insurance if required",
    "certificate_delivery": "Electronic certificate available; electronic state reporting",
    "retake_policy": "Not specified",
    "affiliate_link": "https://courses.ticketschool.com/FL-BDI2/register_2.asp?Aff=434",
    "show_modules": "FALSE",
    "headline": "Become a Safer, Smarter Driver",
    "subhead": "State-approved, mobile-friendly, and 100% online. Finish at your own pace.",
    "hero_cta_label": "Start Now",
    "badge_list": "Mobile Friendly|Instant Certificate|Secure Checkout",
    "faq_set_key": "florida_bdi",
    "terms_url": "/terms",
    "privacy_url": "/privacy",
    "blurb": "Dismiss a ticket and keep points off your record with a state‑approved Basic Driver Improvement course.",
    "stateApproved": true,
    "mobileFriendly": true,
    "instantCertificate": true,
    "satisfactionGuarantee": true,
    "shortestAllowed": true,
    "secureCheckout": true,
    "isPartner": true
  },
  {
    "slug": "fl-bdi-es",
    "state": "FL",
    "course_name": "Florida Basic Driver Improvement (Spanish)",
    "course_type": "BDI",
    "language": "Spanish",
    "provider_type": "Partner",
    "provider_name": "TicketSchool",
    "affiliate_partner": "TicketSchool",
    "partner_badge": "Provided by TicketSchool",
    "duration_hours": "4",
    "price_usd": "24.95",
    "eligibility": "Same as English BDI; eligible once every 12 months and max 5 times lifetime",
    "identity_verification": "10 ID questions; must answer ≥70% correctly during random checks",
    "reporting_method": "Electronic reporting to FL DHSMV after completion; student must notify court/insurance if required",
    "certificate_delivery": "Electronic certificate available; electronic state reporting",
    "retake_policy": "Not specified",
    "affiliate_link": "https://courses.ticketschool.com/FL-BDI2-SP/register_2.asp?Aff=434",
    "show_modules": "FALSE",
    "headline": "Conduce más seguro e inteligente",
    "subhead": "Aprobado por el estado, compatible con móviles y 100% en línea.",
    "hero_cta_label": "Comenzar",
    "badge_list": "Móvil|Certificado instantáneo|Pago seguro",
    "faq_set_key": "florida_bdi",
    "terms_url": "/terms",
    "privacy_url": "/privacy",
    "blurb": "Dismiss a ticket and keep points off your record with a state‑approved Basic Driver Improvement course.",
    "stateApproved": true,
    "mobileFriendly": true,
    "instantCertificate": true,
    "satisfactionGuarantee": true,
    "shortestAllowed": true,
    "secureCheckout": true,
    "isPartner": true
  },
  {
    "slug": "fl-tlsae",
    "state": "FL",
    "course_name": "Florida Drug and Alcohol Course (TLSAE)",
    "course_type": "TLSAE",
    "language": "English",
    "provider_type": "Partner",
    "provider_name": "TicketSchool",
    "affiliate_partner": "TicketSchool",
    "partner_badge": "Provided by TicketSchool",
    "duration_hours": "4",
    "price_usd": "29",
    "eligibility": "Required for first-time drivers (age rules apply)",
    "identity_verification": "10 yes/no ID questions; multiple failures may cause disqualification",
    "reporting_method": "Certificate available; provider may not auto-report",
    "certificate_delivery": "Immediate PDF download if electronic delivery selected",
    "retake_policy": "Not specified",
    "affiliate_link": "https://courses.ticketschool.com/FL-START2/registration/?Aff=434",
    "show_modules": "FALSE",
    "headline": "First-Time Driver? Start Here",
    "subhead": "State-approved TLSAE—learn the essentials, all online.",
    "hero_cta_label": "Enroll Now",
    "badge_list": "State Approved|Mobile Friendly|PDF Certificate",
    "faq_set_key": "florida_tlsae",
    "terms_url": "/terms",
    "privacy_url": "/privacy",
    "blurb": "First‑time driver course covering traffic law and substance education required before your license.",
    "stateApproved": true,
    "mobileFriendly": true,
    "instantCertificate": true,
    "satisfactionGuarantee": true,
    "shortestAllowed": true,
    "secureCheckout": true,
    "isPartner": true
  },
  {
    "slug": "fl-adi",
    "state": "FL",
    "course_name": "Florida Advanced Driver Improvement (ADI)",
    "course_type": "ADI",
    "language": "English",
    "provider_type": "Partner",
    "provider_name": "TicketSchool",
    "affiliate_partner": "TicketSchool",
    "partner_badge": "Provided by TicketSchool",
    "duration_hours": "12",
    "price_usd": "63",
    "eligibility": "For suspensions/reinstatement or court-ordered requirements",
    "identity_verification": "Identity validation per state rules (ID questions during course)",
    "reporting_method": "Provider reports completion electronically to the State of Florida",
    "certificate_delivery": "Electronic Certificate of Completion available immediately",
    "retake_policy": "Not specified",
    "affiliate_link": "https://courses.ticketschool.com/FL-ADI2/registration/?Aff=434",
    "show_modules": "FALSE",
    "headline": "Get Back on the Road",
    "subhead": "12-hour ADI—state-approved and 100% online.",
    "hero_cta_label": "Start ADI",
    "badge_list": "State Approved|E-Certificate|Mobile Friendly",
    "faq_set_key": "florida_adi",
    "terms_url": "/terms",
    "privacy_url": "/privacy",
    "blurb": "12‑hour Advanced Driver Improvement for suspensions/reinstatement or court‑ordered requirements.",
    "stateApproved": true,
    "mobileFriendly": true,
    "instantCertificate": true,
    "satisfactionGuarantee": true,
    "shortestAllowed": false,
    "secureCheckout": true,
    "isPartner": true
  },
  {
    "slug": "fl-idi",
    "state": "FL",
    "course_name": "Florida Intermediate Driver Improvement (IDI)",
    "course_type": "IDI",
    "language": "English",
    "provider_type": "Partner",
    "provider_name": "TicketSchool",
    "affiliate_partner": "TicketSchool",
    "partner_badge": "Provided by TicketSchool",
    "duration_hours": "8",
    "price_usd": "59.95",
    "eligibility": "Court-ordered in some cases; verify local rules",
    "identity_verification": "10 ID questions; failure rate threshold applies",
    "reporting_method": "Student submits certificate to the court/authority",
    "certificate_delivery": "Completion certificate provided to student",
    "retake_policy": "Not specified",
    "affiliate_link": "https://courses.ticketschool.com/FL-IDI2/registration/?Aff=434",
    "show_modules": "FALSE",
    "headline": "Court-Ordered 8-Hour Course",
    "subhead": "Complete online and submit your certificate to the court.",
    "hero_cta_label": "Start IDI",
    "badge_list": "Court Accepted|Mobile Friendly|Certificate Provided",
    "faq_set_key": "florida_idi",
    "terms_url": "/terms",
    "privacy_url": "/privacy",
    "blurb": "8‑hour Intermediate Driver Improvement—complete online and submit your certificate to the court.",
    "stateApproved": true,
    "mobileFriendly": true,
    "instantCertificate": true,
    "satisfactionGuarantee": true,
    "shortestAllowed": false,
    "secureCheckout": true,
    "isPartner": true
  },
  {
    "slug": "fl-exam",
    "state": "FL",
    "course_name": "Florida Driver License Exam (Online)",
    "course_type": "Exam",
    "language": "English",
    "provider_type": "Partner",
    "provider_name": "TicketSchool",
    "affiliate_partner": "TicketSchool",
    "partner_badge": "Provided by TicketSchool",
    "duration_hours": "",
    "price_usd": "24.95",
    "eligibility": "Under 18 eligible; other age rules apply",
    "identity_verification": "Per FL online testing rules; parent proctor form may apply",
    "reporting_method": "Results transmitted to DMV systems",
    "certificate_delivery": "Not applicable (exam result)",
    "retake_policy": "Not specified",
    "affiliate_link": "https://courses.ticketschool.com/flp/Registration?Aff=434",
    "show_modules": "FALSE",
    "headline": "Florida Learner's Permit Test",
    "subhead": "Take your Class E knowledge exam online.",
    "hero_cta_label": "Take the Exam",
    "badge_list": "DMV Approved|Available 24/7",
    "faq_set_key": "florida_exam",
    "terms_url": "/terms",
    "privacy_url": "/privacy",
    "blurb": "Take the official Class E knowledge exam online from home.",
    "stateApproved": true,
    "mobileFriendly": true,
    "instantCertificate": false,
    "satisfactionGuarantee": true,
    "shortestAllowed": false,
    "secureCheckout": true,
    "isPartner": true
  },
  {
    "slug": "il-adult-ed",
    "state": "IL",
    "course_name": "Illinois Adult Driver Education",
    "course_type": "Adult Driver Ed",
    "language": "English",
    "provider_type": "Partner",
    "provider_name": "TicketSchool",
    "affiliate_partner": "TicketSchool",
    "partner_badge": "Provided by TicketSchool",
    "duration_hours": "6",
    "price_usd": "49",
    "eligibility": "Ages 18–20, first-time license, no prior driver ed",
    "identity_verification": "10 ID questions; must pass random checks",
    "reporting_method": "Reported to Illinois SOS",
    "certificate_delivery": "Electronic/SOS record",
    "retake_policy": "Not specified",
    "affiliate_link": "https://courses.ticketschool.com/ilade/Registration?affiliate=434",
    "show_modules": "FALSE",
    "headline": "Get Licensed the Right Way",
    "subhead": "Illinois SOS-approved Adult Driver Education online.",
    "hero_cta_label": "Enroll Now",
    "badge_list": "SOS Approved|Mobile Friendly|Free Reporting",
    "faq_set_key": "illinois_adult_ed",
    "terms_url": "/terms",
    "privacy_url": "/privacy",
    "blurb": "State‑approved driver education for adults; includes the knowledge exam where applicable.",
    "stateApproved": true,
    "mobileFriendly": true,
    "instantCertificate": true,
    "satisfactionGuarantee": true,
    "shortestAllowed": false,
    "secureCheckout": true,
    "isPartner": true
  },
  {
    "slug": "la-di",
    "state": "LA",
    "course_name": "Louisiana Driver Improvement",
    "course_type": "Driver Improvement",
    "language": "English",
    "provider_type": "Partner",
    "provider_name": "TicketSchool",
    "affiliate_partner": "TicketSchool",
    "partner_badge": "Provided by TicketSchool",
    "duration_hours": "6",
    "price_usd": "34.95",
    "eligibility": "Court-approved for ticket dismissal; verify with your court",
    "identity_verification": "10 yes/no ID questions during registration; random checks in-course",
    "reporting_method": "Student typically submits certificate to court",
    "certificate_delivery": "E-certificate available; student delivers to court/insurer",
    "retake_policy": "Must complete within 180 days of registration",
    "affiliate_link": "https://courses.ticketschool.com/LA/registration/?Aff=434",
    "show_modules": "FALSE",
    "headline": "Dismiss Your Ticket Online",
    "subhead": "Court-approved Louisiana Driver Improvement, 100% online.",
    "hero_cta_label": "Start Course",
    "badge_list": "Court Approved|Mobile Friendly|No Timers",
    "faq_set_key": "louisiana_di",
    "terms_url": "/terms",
    "privacy_url": "/privacy",
    "blurb": "Court/DMV‑approved driver improvement to satisfy requirements or reduce points.",
    "stateApproved": true,
    "mobileFriendly": true,
    "instantCertificate": true,
    "satisfactionGuarantee": true,
    "shortestAllowed": false,
    "secureCheckout": true,
    "isPartner": true
  },
  {
    "slug": "mi-bdic",
    "state": "MI",
    "course_name": "Michigan Basic Driver Improvement (BDIC)",
    "course_type": "BDIC",
    "language": "English",
    "provider_type": "Partner",
    "provider_name": "TicketSchool",
    "affiliate_partner": "TicketSchool",
    "partner_badge": "Provided by TicketSchool",
    "duration_hours": "4",
    "price_usd": "34.95",
    "eligibility": "Must be SOS-eligible via letter",
    "identity_verification": "10 yes/no ID questions validated during course",
    "reporting_method": "Provider reports to MI SOS within 1 business day",
    "certificate_delivery": "No final exam; completion recorded with SOS",
    "retake_policy": "Not specified",
    "affiliate_link": "https://courses.ticketschool.com/mi/registration/?Aff=434",
    "show_modules": "FALSE",
    "headline": "Keep Points Off Your Record",
    "subhead": "SOS-approved Michigan BDIC—complete online in about 4 hours.",
    "hero_cta_label": "Start BDIC",
    "badge_list": "SOS Approved|Mobile Friendly|No Final Exam",
    "faq_set_key": "michigan_bdic",
    "terms_url": "/terms",
    "privacy_url": "/privacy",
    "blurb": "Michigan SOS‑approved BDIC to prevent points and insurance increases after eligible tickets.",
    "stateApproved": true,
    "mobileFriendly": true,
    "instantCertificate": true,
    "satisfactionGuarantee": true,
    "shortestAllowed": true,
    "secureCheckout": true,
    "isPartner": true
  },
  {
    "slug": "mo-dip",
    "state": "MO",
    "course_name": "Missouri Driver Improvement Program (DIP)",
    "course_type": "Driver Improvement",
    "language": "English",
    "provider_type": "Partner",
    "provider_name": "TicketSchool",
    "affiliate_partner": "TicketSchool",
    "partner_badge": "Provided by TicketSchool",
    "duration_hours": "8",
    "price_usd": "29.95",
    "eligibility": "Approved statewide; court authorization required",
    "identity_verification": "Standard ID questions during course",
    "reporting_method": "E-certificate; student may submit to court/insurer",
    "certificate_delivery": "Free e-certificate",
    "retake_policy": "Not specified",
    "affiliate_link": "https://courses.ticketschool.com/mo/registration/?Aff=434",
    "show_modules": "FALSE",
    "headline": "Avoid Points in Missouri",
    "subhead": "8-hour DIP approved by Missouri Safety Center.",
    "hero_cta_label": "Start DIP",
    "badge_list": "State Approved|Free E-certificate|Available 24/7",
    "faq_set_key": "missouri_dip",
    "terms_url": "/terms",
    "privacy_url": "/privacy",
    "blurb": "Court/DMV‑approved driver improvement to satisfy requirements or reduce points.",
    "stateApproved": true,
    "mobileFriendly": true,
    "instantCertificate": true,
    "satisfactionGuarantee": true,
    "shortestAllowed": false,
    "secureCheckout": true,
    "isPartner": true
  },
  {
    "slug": "ny-ipirp",
    "state": "NY",
    "course_name": "New York Defensive Driving (IPIRP)",
    "course_type": "IPIRP",
    "language": "English",
    "provider_type": "Partner",
    "provider_name": "TicketSchool",
    "affiliate_partner": "TicketSchool",
    "partner_badge": "Provided by TicketSchool",
    "duration_hours": "5.5",
    "price_usd": "24.95",
    "eligibility": "4-point reduction and 10% insurance discount",
    "identity_verification": "Login ID + phone call-in checkpoints",
    "reporting_method": "Original completion certificate mailed; DMV handles point reduction",
    "certificate_delivery": "Original certificate mailed (US Mail or overnight options)",
    "retake_policy": "Unit quizzes with multiple attempts",
    "affiliate_link": "https://courses.ticketschool.com/nysdd/Registration/Step1?affiliate=434",
    "show_modules": "FALSE",
    "headline": "Save on Insurance & Reduce Points",
    "subhead": "DMV-approved New York IPIRP online.",
    "hero_cta_label": "Start Course",
    "badge_list": "DMV Approved|Insurance Discount|Point Reduction",
    "faq_set_key": "newyork_ipirp",
    "terms_url": "/terms",
    "privacy_url": "/privacy",
    "blurb": "DMV‑approved defensive driving for insurance discount and point reduction in New York.",
    "stateApproved": true,
    "mobileFriendly": true,
    "instantCertificate": false,
    "satisfactionGuarantee": true,
    "shortestAllowed": false,
    "secureCheckout": true,
    "isPartner": true
  },
  {
    "slug": "ny-5hr",
    "state": "NY",
    "course_name": "New York Online Pre-Licensing (5-hour)",
    "course_type": "Pre-Licensing",
    "language": "English",
    "provider_type": "Partner",
    "provider_name": "TicketSchool",
    "affiliate_partner": "TicketSchool",
    "partner_badge": "Provided by TicketSchool",
    "duration_hours": "4.5",
    "price_usd": "49",
    "eligibility": "Age 18+; complete within 30 days of registration",
    "identity_verification": "10 ID questions + phone call system; 3 failed attempts => disqualification",
    "reporting_method": "Completion reported electronically to NY DMV within 24–48 hours",
    "certificate_delivery": "No certificate; DMV record updated",
    "retake_policy": "Unit quizzes 70% to pass; 3 attempts per unit",
    "affiliate_link": "https://courses.ticketschool.com/nys/Registration/Step1?affiliate=434",
    "show_modules": "FALSE",
    "headline": "NY 5‑Hour Pre‑Licensing",
    "subhead": "Meet the DMV requirement online and schedule your road test.",
    "hero_cta_label": "Start 5‑Hour Course",
    "badge_list": "DMV Approved|No Final Exam|24/7 Access",
    "faq_set_key": "newyork_prelicensing",
    "terms_url": "/terms",
    "privacy_url": "/privacy",
    "blurb": "New York 5‑hour pre‑licensing course required before scheduling your road test.",
    "stateApproved": true,
    "mobileFriendly": true,
    "instantCertificate": false,
    "satisfactionGuarantee": true,
    "shortestAllowed": false,
    "secureCheckout": true,
    "isPartner": true
  },
  {
    "slug": "tn-driver-ed",
    "state": "TN",
    "course_name": "Tennessee Online Driver Education Course",
    "course_type": "Driver Education",
    "language": "English",
    "provider_type": "Partner",
    "provider_name": "TicketSchool",
    "affiliate_partner": "TicketSchool",
    "partner_badge": "Provided by TicketSchool",
    "duration_hours": "4",
    "price_usd": "29.95",
    "eligibility": "TDOS-approved; ticket dismissal or point reduction (with court approval)",
    "identity_verification": "10 ID questions; random checks during course",
    "reporting_method": "Electronic certificate; submit to court/insurer as required",
    "certificate_delivery": "Electronic certificate (PDF) after completion",
    "retake_policy": "Not specified",
    "affiliate_link": "https://courses.ticketschool.com/TN/registration/?Aff=434",
    "show_modules": "FALSE",
    "headline": "Dismiss Your Ticket in Tennessee",
    "subhead": "4-hour TDOS-approved online driver education.",
    "hero_cta_label": "Start Course",
    "badge_list": "State Approved|E-Certificate|No Final Exam",
    "faq_set_key": "tennessee_driver_ed",
    "terms_url": "/terms",
    "privacy_url": "/privacy",
    "blurb": "4‑hour state‑approved driver education; mobile‑friendly with instant certificate.",
    "stateApproved": true,
    "mobileFriendly": true,
    "instantCertificate": true,
    "satisfactionGuarantee": true,
    "shortestAllowed": true,
    "secureCheckout": true,
    "isPartner": true
  },
  {
    "slug": "tx-defensive",
    "state": "TX",
    "course_name": "Texas Defensive Driving",
    "course_type": "Defensive Driving",
    "language": "English",
    "provider_type": "Partner",
    "provider_name": "TicketSchool",
    "affiliate_partner": "TicketSchool",
    "partner_badge": "Provided by TicketSchool",
    "duration_hours": "6",
    "price_usd": "25",
    "eligibility": "TDLR-approved; ticket dismissal with court approval; insurance discount",
    "identity_verification": "10 ID questions from DL/registration data; ≥70% to pass checks",
    "reporting_method": "Emailed certificate (free); student submits to court/insurer",
    "certificate_delivery": "Free electronic certificate by email",
    "retake_policy": "Not specified",
    "affiliate_link": "https://courses.ticketschool.com/TEX/register_2.asp?Aff=434",
    "qa_link": "https://app.qa.roadreadysafety.com/public/checkout?sku=tx-bdi",
    "show_modules": "FALSE",
    "headline": "Dismiss Your Ticket the Easy Way",
    "subhead": "6-hour TDLR-approved defensive driving—certificate emailed free.",
    "hero_cta_label": "Start Course",
    "badge_list": "TDLR Approved|Free E‑Certificate|Mobile Friendly",
    "faq_set_key": "texas_defensive",
    "terms_url": "/terms",
    "privacy_url": "/privacy",
    "blurb": "State‑approved defensive driving for ticket dismissal and insurance savings.",
    "stateApproved": true,
    "mobileFriendly": true,
    "instantCertificate": true,
    "satisfactionGuarantee": true,
    "shortestAllowed": false,
    "secureCheckout": true,
    "isPartner": true
  },
  {
    "slug": "tx-adult-ed",
    "state": "TX",
    "course_name": "Texas Adult Driver Education",
    "course_type": "Adult Driver Ed",
    "language": "English",
    "provider_type": "Partner",
    "provider_name": "TicketSchool",
    "affiliate_partner": "TicketSchool",
    "partner_badge": "Provided by TicketSchool",
    "duration_hours": "6",
    "price_usd": "29.95",
    "eligibility": "Required for drivers age 18–24; recommended for 25+; includes DPS written exam",
    "identity_verification": "10 ID questions; must answer ≥70% during random checks",
    "reporting_method": "E-certificate; student proceeds to DPS per state process",
    "certificate_delivery": "E-certificate (PDF) included",
    "retake_policy": "Not specified",
    "affiliate_link": "https://courses.ticketschool.com/txade/Registration?affiliate=434",
    "show_modules": "FALSE",
    "headline": "Adult Driver Ed (18–24)",
    "subhead": "6-hour TDLR-approved course—DPS knowledge exam included.",
    "hero_cta_label": "Start Adult Ed",
    "badge_list": "State Approved|DPS Test Included|E‑Certificate",
    "faq_set_key": "texas_adult_ed",
    "terms_url": "/terms",
    "privacy_url": "/privacy",
    "blurb": "State‑approved driver education for adults; includes the knowledge exam where applicable.",
    "stateApproved": true,
    "mobileFriendly": true,
    "instantCertificate": true,
    "satisfactionGuarantee": true,
    "shortestAllowed": false,
    "secureCheckout": true,
    "isPartner": true
  },
  {
    "slug": "va-driver-improvement",
    "state": "VA",
    "course_name": "Virginia Driver Improvement",
    "course_type": "Driver Improvement",
    "language": "English",
    "provider_type": "Partner",
    "provider_name": "TicketSchool",
    "affiliate_partner": "TicketSchool",
    "partner_badge": "Provided by TicketSchool",
    "duration_hours": "8",
    "price_usd": "34.95",
    "eligibility": "DMV-approved; court-ordered, insurance discount, or safe driver points",
    "identity_verification": "10 ID questions; random checks; multiple failures may disqualify",
    "reporting_method": "Free reporting to VA DMV; certificate PDF available immediately",
    "certificate_delivery": "E-certificate (PDF) immediately after completion",
    "retake_policy": "Not specified",
    "affiliate_link": "https://courses.ticketschool.com/VA2/registration/?Aff=434",
    "show_modules": "FALSE",
    "headline": "Virginia Driver Improvement Clinic",
    "subhead": "8-hour DMV-approved online course with free DMV reporting.",
    "hero_cta_label": "Start Course",
    "badge_list": "DMV Approved|E‑Certificate|Free DMV Reporting",
    "faq_set_key": "virginia_driver_improvement",
    "terms_url": "/terms",
    "privacy_url": "/privacy",
    "blurb": "Court/DMV‑approved driver improvement to satisfy requirements or reduce points.",
    "stateApproved": true,
    "mobileFriendly": true,
    "instantCertificate": true,
    "satisfactionGuarantee": true,
    "shortestAllowed": false,
    "secureCheckout": true,
    "isPartner": true
  }
]